[
    {
        "id": 289,
        "partner_type": "Government",
        "cso_type": null,
        "name": "REGIONAL EXPANDED PROGRAMME ON MANAGEMENT TEAM - CENTRAL REGION",
        "short_name": "",
        "description": "",
        "shared_partner": "No",
        "address": null,
        "email": null,
        "phone_number": "700264172",
        "vendor_number": 2500217202,
        "alternate_id": null,
        "alternate_name": null,
        "rating": "High",
        "type_of_assessment": null,
        "last_assessment_date": null,
        "core_values_assessment_date": null,
        "core_values_assessment": null,
        "vision_synced": true
    },
    {
        "id": 195,
        "partner_type": "Government",
        "cso_type": null,
        "name": "REMT-CENTRAL REGION",
        "short_name": "",
        "description": "",
        "shared_partner": "No",
        "address": "DARWAZA LAHORI DIS 01,KABUL",
        "email": "KPHD.EPI.OSS@GMAIL",
        "phone_number": "07005078483",
        "vendor_number": 2500220521,
        "alternate_id": null,
        "alternate_name": null,
        "rating": "High",
        "type_of_assessment": "High Risk Assumed",
        "last_assessment_date": "2016-01-20",
        "core_values_assessment_date": null,
        "core_values_assessment": null,
        "vision_synced": true
    },
    {
        "id": 213,
        "partner_type": "Government",
        "cso_type": null,
        "name": "RIASAT SEHAT HAMA TAKHAR",
        "short_name": "",
        "description": "",
        "shared_partner": "No",
        "address": null,
        "email": null,
        "phone_number": null,
        "vendor_number": 2500217160,
        "alternate_id": null,
        "alternate_name": null,
        "rating": "High",
        "type_of_assessment": "High Risk Assumed",
        "last_assessment_date": "2016-10-09",
        "core_values_assessment_date": null,
        "core_values_assessment": null,
        "vision_synced": true
    },
    {
        "id": 616,
        "partner_type": "Government",
        "cso_type": null,
        "name": "RRD BADAKHSHAN",
        "short_name": "",
        "description": "",
        "shared_partner": "No",
        "address": "NEW CITY STREET",
        "email": "NASEER.BDK@GAMIL.COM",
        "phone_number": "0799477211",
        "vendor_number": 2500234421,
        "alternate_id": null,
        "alternate_name": null,
        "rating": "Moderate",
        "type_of_assessment": "Simplified Checklist",
        "last_assessment_date": "2015-07-29",
        "core_values_assessment_date": null,
        "core_values_assessment": null,
        "vision_synced": true
    },
    {
        "id": 753,
        "partner_type": "Government",
        "cso_type": null,
        "name": "RRD OF SAR-E- PULL",
        "short_name": "",
        "description": "",
        "shared_partner": "No",
        "address": "SARPULL SAR E PULL SHAR-E- NOW",
        "email": null,
        "phone_number": "0777158696",
        "vendor_number": 2500222240,
        "alternate_id": null,
        "alternate_name": null,
        "rating": "High",
        "type_of_assessment": null,
        "last_assessment_date": null,
        "core_values_assessment_date": null,
        "core_values_assessment": null,
        "vision_synced": true
    },
    {
        "id": 832,
        "partner_type": "Government",
        "cso_type": null,
        "name": "RRD SAMANGAN",
        "short_name": "",
        "description": "",
        "shared_partner": "No",
        "address": "SAMANGAN SAMANGAN CITY",
        "email": null,
        "phone_number": null,
        "vendor_number": 2500222178,
        "alternate_id": null,
        "alternate_name": null,
        "rating": "High",
        "type_of_assessment": null,
        "last_assessment_date": null,
        "core_values_assessment_date": null,
        "core_values_assessment": null,
        "vision_synced": true
    },
    {
        "id": 424,
        "partner_type": "Government",
        "cso_type": null,
        "name": "RURAL REHABILITATION AND DEVELOPMEN OF BALKH",
        "short_name": "",
        "description": "",
        "shared_partner": "No",
        "address": null,
        "email": null,
        "phone_number": null,
        "vendor_number": 2500217322,
        "alternate_id": null,
        "alternate_name": null,
        "rating": "High",
        "type_of_assessment": null,
        "last_assessment_date": null,
        "core_values_assessment_date": null,
        "core_values_assessment": null,
        "vision_synced": true
    },
    {
        "id": 175,
        "partner_type": "Government",
        "cso_type": null,
        "name": "RURAL REHABILITATION DEPARTMENT  HERAT",
        "short_name": "",
        "description": "",
        "shared_partner": "No",
        "address": "HERAT CITY",
        "email": null,
        "phone_number": null,
        "vendor_number": 2500200206,
        "alternate_id": null,
        "alternate_name": null,
        "rating": "High",
        "type_of_assessment": "High Risk Assumed",
        "last_assessment_date": "2016-01-20",
        "core_values_assessment_date": null,
        "core_values_assessment": null,
        "vision_synced": true
    },
    {
        "id": 476,
        "partner_type": "Government",
        "cso_type": null,
        "name": "SABT WA AHWAL NOFO SAMANGAN",
        "short_name": "",
        "description": "",
        "shared_partner": "No",
        "address": "CENTER OF AYBAK",
        "email": null,
        "phone_number": "075774956",
        "vendor_number": 2500228668,
        "alternate_id": null,
        "alternate_name": null,
        "rating": "High",
        "type_of_assessment": "High Risk Assumed",
        "last_assessment_date": "2016-01-04",
        "core_values_assessment_date": null,
        "core_values_assessment": null,
        "vision_synced": true
    },
    {
        "id": 598,
        "partner_type": "Government",
        "cso_type": null,
        "name": "SADIA AYUBI",
        "short_name": "",
        "description": "",
        "shared_partner": "No",
        "address": "GOLAYEE- EHAS 1 KHAIKHANA",
        "email": "AYUBISADIA@YAHOO.COM",
        "phone_number": "202302453",
        "vendor_number": 2300065263,
        "alternate_id": null,
        "alternate_name": null,
        "rating": null,
        "type_of_assessment": null,
        "last_assessment_date": null,
        "core_values_assessment_date": null,
        "core_values_assessment": null,
        "vision_synced": true
    },
    {
        "id": 511,
        "partner_type": "Government",
        "cso_type": null,
        "name": "SAD MARDA CDC",
        "short_name": "",
        "description": "",
        "shared_partner": "No",
        "address": "SAD MARDA VILLAGE",
        "email": null,
        "phone_number": "0797473980",
        "vendor_number": 2500229200,
        "alternate_id": null,
        "alternate_name": null,
        "rating": "High",
        "type_of_assessment": "High Risk Assumed",
        "last_assessment_date": "2016-01-04",
        "core_values_assessment_date": null,
        "core_values_assessment": null,
        "vision_synced": true
    },
    {
        "id": 542,
        "partner_type": "Government",
        "cso_type": null,
        "name": "SAID HABIB ARWAL",
        "short_name": "",
        "description": "",
        "shared_partner": "No",
        "address": "SHASHDARAK AREA 9 DISTRICT KAB",
        "email": "SAIDHABIBA@GMAIL.COM",
        "phone_number": "0700605071",
        "vendor_number": 2300065271,
        "alternate_id": null,
        "alternate_name": null,
        "rating": null,
        "type_of_assessment": null,
        "last_assessment_date": null,
        "core_values_assessment_date": null,
        "core_values_assessment": null,
        "vision_synced": true
    },
    {
        "id": 75,
        "partner_type": "Civil Society Organization",
        "cso_type": "National",
        "name": "SANAYEE DEVELOPMENT ORGANIZATION",
        "short_name": "",
        "description": "",
        "shared_partner": "No",
        "address": "GHAZNI CITY CENTER",
        "email": null,
        "phone_number": "0700220638",
        "vendor_number": 2300063860,
        "alternate_id": null,
        "alternate_name": null,
        "rating": null,
        "type_of_assessment": null,
        "last_assessment_date": null,
        "core_values_assessment_date": null,
        "core_values_assessment": null,
        "vision_synced": true
    },
    {
        "id": 679,
        "partner_type": "Government",
        "cso_type": null,
        "name": "SAR-I-POL ECONOMY DEP",
        "short_name": "",
        "description": "",
        "shared_partner": "No",
        "address": "SAR-E-POL",
        "email": null,
        "phone_number": "0799104811",
        "vendor_number": 2500228579,
        "alternate_id": null,
        "alternate_name": null,
        "rating": "High",
        "type_of_assessment": "High Risk Assumed",
        "last_assessment_date": "2016-01-04",
        "core_values_assessment_date": null,
        "core_values_assessment": null,
        "vision_synced": true
    },
    {
        "id": 829,
        "partner_type": "Government",
        "cso_type": null,
        "name": "SARKANI ZEYARAT C.D.C",
        "short_name": "",
        "description": "",
        "shared_partner": "No",
        "address": "ORUZGAN SARKANI ZEYARAT VILLAG",
        "email": null,
        "phone_number": "0797073913",
        "vendor_number": 2500229594,
        "alternate_id": null,
        "alternate_name": null,
        "rating": "High",
        "type_of_assessment": "High Risk Assumed",
        "last_assessment_date": "2016-01-04",
        "core_values_assessment_date": null,
        "core_values_assessment": null,
        "vision_synced": true
    },
    {
        "id": 3,
        "partner_type": "Civil Society Organization",
        "cso_type": "International",
        "name": "SAVE THE CHILDREN INTERNATIONAL",
        "short_name": "",
        "description": "",
        "shared_partner": "No",
        "address": "HOUSE NO. 321 STREET 4",
        "email": "FAISAL.ZAREEN@SAVETHECHILDREN.ORG",
        "phone_number": "93 (0) 799 89...",
        "vendor_number": 2500215280,
        "alternate_id": null,
        "alternate_name": null,
        "rating": "High",
        "type_of_assessment": "High Risk Assumed",
        "last_assessment_date": "2011-09-07",
        "core_values_assessment_date": "2013-07-23",
        "core_values_assessment": null,
        "vision_synced": true
    },
    {
        "id": 86,
        "partner_type": "Civil Society Organization",
        "cso_type": "International",
        "name": "SAVE THE CHILDREN-UK",
        "short_name": "",
        "description": "",
        "shared_partner": "No",
        "address": "1ST JOHN'S LAN, LONDON, EC1M4A",
        "email": "CPD.AFGHANISTAN@GMAIL.COM",
        "phone_number": "799521056",
        "vendor_number": 2500217181,
        "alternate_id": null,
        "alternate_name": null,
        "rating": null,
        "type_of_assessment": null,
        "last_assessment_date": null,
        "core_values_assessment_date": null,
        "core_values_assessment": null,
        "vision_synced": true
    },
    {
        "id": 581,
        "partner_type": "Government",
        "cso_type": null,
        "name": "SAWKI KANSTOR KALI SAGANI CDC P",
        "short_name": "",
        "description": "",
        "shared_partner": "No",
        "address": "KUNAR SAWKI DISTRICT",
        "email": null,
        "phone_number": null,
        "vendor_number": 2500229786,
        "alternate_id": null,
        "alternate_name": null,
        "rating": "High",
        "type_of_assessment": "High Risk Assumed",
        "last_assessment_date": "2016-01-04",
        "core_values_assessment_date": null,
        "core_values_assessment": null,
        "vision_synced": true
    },
    {
        "id": 362,
        "partner_type": "Government",
        "cso_type": null,
        "name": "SAWKY DDA",
        "short_name": "",
        "description": "",
        "shared_partner": "No",
        "address": "SAWKY DISTRICT KUNAR",
        "email": null,
        "phone_number": "0774238456",
        "vendor_number": 2500229738,
        "alternate_id": null,
        "alternate_name": null,
        "rating": "High",
        "type_of_assessment": "High Risk Assumed",
        "last_assessment_date": "2016-01-04",
        "core_values_assessment_date": null,
        "core_values_assessment": null,
        "vision_synced": true
    },
    {
        "id": 627,
        "partner_type": "Government",
        "cso_type": null,
        "name": "SAYED ALISHAH ALWAI",
        "short_name": "",
        "description": "",
        "shared_partner": "No",
        "address": "HESA 2 KHAIRKHANA",
        "email": "SALAWIDR@GMAIL.COM",
        "phone_number": "0700290136",
        "vendor_number": 2300065251,
        "alternate_id": null,
        "alternate_name": null,
        "rating": null,
        "type_of_assessment": null,
        "last_assessment_date": null,
        "core_values_assessment_date": null,
        "core_values_assessment": null,
        "vision_synced": true
    },
    {
        "id": 945,
        "partner_type": "Government",
        "cso_type": null,
        "name": "SAYED FAROOQ",
        "short_name": "",
        "description": "",
        "shared_partner": "No",
        "address": "DARWAZ-E- LAHORI KABUL CITY",
        "email": "NATIONALEPI@GMAIL.COM",
        "phone_number": "0778137069",
        "vendor_number": 2300065365,
        "alternate_id": null,
        "alternate_name": null,
        "rating": null,
        "type_of_assessment": null,
        "last_assessment_date": null,
        "core_values_assessment_date": null,
        "core_values_assessment": null,
        "vision_synced": true
    },
    {
        "id": 488,
        "partner_type": "Government",
        "cso_type": null,
        "name": "SAYED MOHIB ALI",
        "short_name": "",
        "description": "",
        "shared_partner": "No",
        "address": "KABUL",
        "email": null,
        "phone_number": null,
        "vendor_number": 2300043108,
        "alternate_id": null,
        "alternate_name": null,
        "rating": null,
        "type_of_assessment": "MICRO ASST.",
        "last_assessment_date": "2011-12-30",
        "core_values_assessment_date": null,
        "core_values_assessment": null,
        "vision_synced": true
    },
    {
        "id": 584,
        "partner_type": "Government",
        "cso_type": null,
        "name": "SAYED WAHIDULLAH",
        "short_name": "",
        "description": "",
        "shared_partner": "No",
        "address": "KABUL",
        "email": null,
        "phone_number": null,
        "vendor_number": 2300043107,
        "alternate_id": null,
        "alternate_name": null,
        "rating": null,
        "type_of_assessment": "MICRO ASST.",
        "last_assessment_date": "2011-12-30",
        "core_values_assessment_date": null,
        "core_values_assessment": null,
        "vision_synced": true
    },
    {
        "id": 49,
        "partner_type": "Civil Society Organization",
        "cso_type": "National",
        "name": "SERVE HEALTH RELIEF AND DEVELOPMENT (SHRDO)",
        "short_name": "",
        "description": "",
        "shared_partner": "No",
        "address": "H 8, STREET 9 SECTOR A, KHOS",
        "email": "SHRDO.KABUL@GMAIL.COM",
        "phone_number": "0799568108",
        "vendor_number": 2300042808,
        "alternate_id": null,
        "alternate_name": null,
        "rating": null,
        "type_of_assessment": null,
        "last_assessment_date": null,
        "core_values_assessment_date": null,
        "core_values_assessment": null,
        "vision_synced": true
    },
    {
        "id": 147,
        "partner_type": "Government",
        "cso_type": null,
        "name": "SHAH GUL QAMARI",
        "short_name": "",
        "description": "",
        "shared_partner": "No",
        "address": "MOE KABUL CITY",
        "email": null,
        "phone_number": null,
        "vendor_number": 2500223288,
        "alternate_id": null,
        "alternate_name": null,
        "rating": "Non-Assessed",
        "type_of_assessment": "Micro Assessment",
        "last_assessment_date": "2011-12-31",
        "core_values_assessment_date": null,
        "core_values_assessment": null,
        "vision_synced": true
    },
    {
        "id": 441,
        "partner_type": "Government",
        "cso_type": null,
        "name": "SHAH JOI DDA",
        "short_name": "",
        "description": "",
        "shared_partner": "No",
        "address": "NEW JAMAH DISTRICT SHAHJOI",
        "email": null,
        "phone_number": "07085755403",
        "vendor_number": 2500229268,
        "alternate_id": null,
        "alternate_name": null,
        "rating": "High",
        "type_of_assessment": "High Risk Assumed",
        "last_assessment_date": "2016-01-04",
        "core_values_assessment_date": null,
        "core_values_assessment": null,
        "vision_synced": true
    },
    {
        "id": 747,
        "partner_type": "Government",
        "cso_type": null,
        "name": "SHAHRE SAFA D.D.A",
        "short_name": "",
        "description": "",
        "shared_partner": "No",
        "address": "ZABUL PROVINCE",
        "email": null,
        "phone_number": null,
        "vendor_number": 2500227310,
        "alternate_id": null,
        "alternate_name": null,
        "rating": "Non-Assessed",
        "type_of_assessment": "Micro Assessment",
        "last_assessment_date": null,
        "core_values_assessment_date": null,
        "core_values_assessment": null,
        "vision_synced": true
    },
    {
        "id": 177,
        "partner_type": "Government",
        "cso_type": null,
        "name": "SHE DDA IMAM SAHIB/KUNDUZ",
        "short_name": "",
        "description": "",
        "shared_partner": "No",
        "address": "KUNDUZ",
        "email": null,
        "phone_number": null,
        "vendor_number": 2500224342,
        "alternate_id": null,
        "alternate_name": null,
        "rating": "High",
        "type_of_assessment": null,
        "last_assessment_date": null,
        "core_values_assessment_date": null,
        "core_values_assessment": null,
        "vision_synced": true
    },
    {
        "id": 513,
        "partner_type": "Government",
        "cso_type": null,
        "name": "SH E DDA QALAIZAL/KUNDUZ",
        "short_name": "",
        "description": "",
        "shared_partner": "No",
        "address": "KUNDUZ KUNDUZ CITY",
        "email": null,
        "phone_number": null,
        "vendor_number": 2500223237,
        "alternate_id": null,
        "alternate_name": null,
        "rating": "High",
        "type_of_assessment": null,
        "last_assessment_date": null,
        "core_values_assessment_date": null,
        "core_values_assessment": null,
        "vision_synced": true
    },
    {
        "id": 472,
        "partner_type": "Government",
        "cso_type": null,
        "name": "SHINKAI D.D.A",
        "short_name": "",
        "description": "",
        "shared_partner": "No",
        "address": "ZABUL CITY CENTER",
        "email": null,
        "phone_number": null,
        "vendor_number": 2500226470,
        "alternate_id": null,
        "alternate_name": null,
        "rating": "High",
        "type_of_assessment": "High Risk Assumed",
        "last_assessment_date": "2016-01-04",
        "core_values_assessment_date": null,
        "core_values_assessment": null,
        "vision_synced": true
    },
    {
        "id": 431,
        "partner_type": "Government",
        "cso_type": null,
        "name": "SHORA ENKISHAFI WALOS WALI KHAN ABAD",
        "short_name": "",
        "description": "",
        "shared_partner": "No",
        "address": "KHAN ABAD",
        "email": null,
        "phone_number": "0795157741",
        "vendor_number": 2500229301,
        "alternate_id": null,
        "alternate_name": null,
        "rating": null,
        "type_of_assessment": null,
        "last_assessment_date": null,
        "core_values_assessment_date": null,
        "core_values_assessment": null,
        "vision_synced": true
    },
    {
        "id": 913,
        "partner_type": "Government",
        "cso_type": null,
        "name": "SHORAI INKASHAFI (DDA MEHTERLAM)",
        "short_name": "",
        "description": "",
        "shared_partner": "No",
        "address": "MEHTERLAM",
        "email": null,
        "phone_number": null,
        "vendor_number": 2500223899,
        "alternate_id": null,
        "alternate_name": null,
        "rating": "High",
        "type_of_assessment": "High Risk Assumed",
        "last_assessment_date": "2016-01-07",
        "core_values_assessment_date": null,
        "core_values_assessment": null,
        "vision_synced": true
    },
    {
        "id": 547,
        "partner_type": "Government",
        "cso_type": null,
        "name": "SHORAI WOLESWALI BALA MORGHAB",
        "short_name": "",
        "description": "",
        "shared_partner": "No",
        "address": "BADGHIS CITY CENTER",
        "email": null,
        "phone_number": null,
        "vendor_number": 2500227490,
        "alternate_id": null,
        "alternate_name": null,
        "rating": "High",
        "type_of_assessment": "High Risk Assumed",
        "last_assessment_date": "2016-01-04",
        "core_values_assessment_date": null,
        "core_values_assessment": null,
        "vision_synced": true
    },
    {
        "id": 738,
        "partner_type": "Government",
        "cso_type": null,
        "name": "SHURA E ENKASHAFI DAIJA",
        "short_name": "",
        "description": "",
        "shared_partner": "No",
        "address": "DAIJAN VILLAGE AABKAMARI DISTR",
        "email": null,
        "phone_number": "0799078692",
        "vendor_number": 2500228824,
        "alternate_id": null,
        "alternate_name": null,
        "rating": "High",
        "type_of_assessment": "High Risk Assumed",
        "last_assessment_date": "2016-01-04",
        "core_values_assessment_date": null,
        "core_values_assessment": null,
        "vision_synced": true
    },
    {
        "id": 373,
        "partner_type": "Government",
        "cso_type": null,
        "name": "SHURA E ENKASHAFI QARIA ABDUL ABAD",
        "short_name": "",
        "description": "",
        "shared_partner": "No",
        "address": "ABDUL ABAD VILLAGE",
        "email": null,
        "phone_number": "0799095499",
        "vendor_number": 2500229212,
        "alternate_id": null,
        "alternate_name": null,
        "rating": "High",
        "type_of_assessment": "High Risk Assumed",
        "last_assessment_date": "2016-01-04",
        "core_values_assessment_date": null,
        "core_values_assessment": null,
        "vision_synced": true
    },
    {
        "id": 770,
        "partner_type": "Government",
        "cso_type": null,
        "name": "SHURA E ENKASHAFI SAYE",
        "short_name": "",
        "description": "",
        "shared_partner": "No",
        "address": "SAHYEED SHARAF VILLAGE",
        "email": null,
        "phone_number": "0799078692",
        "vendor_number": 2500229210,
        "alternate_id": null,
        "alternate_name": null,
        "rating": "Non-Assessed",
        "type_of_assessment": "Micro Assessment",
        "last_assessment_date": null,
        "core_values_assessment_date": null,
        "core_values_assessment": null,
        "vision_synced": true
    },
    {
        "id": 366,
        "partner_type": "Government",
        "cso_type": null,
        "name": "SHURA E ENKASHAFI SULTAN",
        "short_name": "",
        "description": "",
        "shared_partner": "No",
        "address": "SULTAN HAA VILLAGE, QADIS DIST",
        "email": null,
        "phone_number": "0799078692",
        "vendor_number": 2500228823,
        "alternate_id": null,
        "alternate_name": null,
        "rating": "High",
        "type_of_assessment": "High Risk Assumed",
        "last_assessment_date": "2016-01-04",
        "core_values_assessment_date": null,
        "core_values_assessment": null,
        "vision_synced": true
    },
    {
        "id": 867,
        "partner_type": "Government",
        "cso_type": null,
        "name": "SHURA E ENKASHAFI TAKA",
        "short_name": "",
        "description": "",
        "shared_partner": "No",
        "address": "TAKAK VILLAGE",
        "email": null,
        "phone_number": "0799078692",
        "vendor_number": 2500229211,
        "alternate_id": null,
        "alternate_name": null,
        "rating": "High",
        "type_of_assessment": "High Risk Assumed",
        "last_assessment_date": "2016-01-04",
        "core_values_assessment_date": null,
        "core_values_assessment": null,
        "vision_synced": true
    },
    {
        "id": 773,
        "partner_type": "Government",
        "cso_type": null,
        "name": "SHURA E ENKESHAFI QARA",
        "short_name": "",
        "description": "",
        "shared_partner": "No",
        "address": "ZAOURI VILLAGE QADIS DISTRICT",
        "email": null,
        "phone_number": "0799078692",
        "vendor_number": 2500228830,
        "alternate_id": null,
        "alternate_name": null,
        "rating": "High",
        "type_of_assessment": "High Risk Assumed",
        "last_assessment_date": "2016-01-04",
        "core_values_assessment_date": null,
        "core_values_assessment": null,
        "vision_synced": true
    },
    {
        "id": 490,
        "partner_type": "Government",
        "cso_type": null,
        "name": "SHURAI DDA MARKAZI  CHAYAB/TAKHAR",
        "short_name": "",
        "description": "",
        "shared_partner": "No",
        "address": "TAKHAR CITY",
        "email": null,
        "phone_number": null,
        "vendor_number": 2500223778,
        "alternate_id": null,
        "alternate_name": null,
        "rating": "High",
        "type_of_assessment": null,
        "last_assessment_date": null,
        "core_values_assessment_date": null,
        "core_values_assessment": null,
        "vision_synced": true
    },
    {
        "id": 812,
        "partner_type": "Government",
        "cso_type": null,
        "name": "SHURAI ENKESHAFI DDA ASHKAMASH/TAKH",
        "short_name": "",
        "description": "",
        "shared_partner": "No",
        "address": "TAKHAR CITY",
        "email": null,
        "phone_number": null,
        "vendor_number": 2500223779,
        "alternate_id": null,
        "alternate_name": null,
        "rating": "High",
        "type_of_assessment": null,
        "last_assessment_date": null,
        "core_values_assessment_date": null,
        "core_values_assessment": null,
        "vision_synced": true
    },
    {
        "id": 604,
        "partner_type": "Government",
        "cso_type": null,
        "name": "SHURAI ENKESHAFI QARIA BADGISI/FARY",
        "short_name": "",
        "description": "",
        "shared_partner": "No",
        "address": "FARYAB",
        "email": null,
        "phone_number": null,
        "vendor_number": 2500224204,
        "alternate_id": null,
        "alternate_name": null,
        "rating": "High",
        "type_of_assessment": null,
        "last_assessment_date": null,
        "core_values_assessment_date": null,
        "core_values_assessment": null,
        "vision_synced": true
    },
    {
        "id": 281,
        "partner_type": "Government",
        "cso_type": null,
        "name": "SHURAI ENKESHAFI QARIA FAKHRAK TAKHAR",
        "short_name": "",
        "description": "",
        "shared_partner": "No",
        "address": "TAKHAR CITY",
        "email": null,
        "phone_number": null,
        "vendor_number": 2500224354,
        "alternate_id": null,
        "alternate_name": null,
        "rating": "High",
        "type_of_assessment": null,
        "last_assessment_date": null,
        "core_values_assessment_date": null,
        "core_values_assessment": null,
        "vision_synced": true
    },
    {
        "id": 341,
        "partner_type": "Government",
        "cso_type": null,
        "name": "SHURAI ENKESHAFI QARIA INJALAD FARYAB",
        "short_name": "",
        "description": "",
        "shared_partner": "No",
        "address": "FARYAB",
        "email": null,
        "phone_number": null,
        "vendor_number": 2500224202,
        "alternate_id": null,
        "alternate_name": null,
        "rating": "High",
        "type_of_assessment": "High Risk Assumed",
        "last_assessment_date": "2016-01-04",
        "core_values_assessment_date": null,
        "core_values_assessment": null,
        "vision_synced": true
    },
    {
        "id": 697,
        "partner_type": "Government",
        "cso_type": null,
        "name": "SHURAI ENKESHAFI QARIA SHEKARDARA",
        "short_name": "",
        "description": "",
        "shared_partner": "No",
        "address": "FARAH",
        "email": null,
        "phone_number": "0799459865",
        "vendor_number": 2500230035,
        "alternate_id": null,
        "alternate_name": null,
        "rating": "High",
        "type_of_assessment": "High Risk Assumed",
        "last_assessment_date": "2016-01-04",
        "core_values_assessment_date": null,
        "core_values_assessment": null,
        "vision_synced": true
    },
    {
        "id": 550,
        "partner_type": "Government",
        "cso_type": null,
        "name": "SIFATULLAH RAHIMIEE",
        "short_name": "",
        "description": "",
        "shared_partner": "No",
        "address": "MICRORAYON DIS- 9 KABUL CITY",
        "email": null,
        "phone_number": null,
        "vendor_number": 2300060856,
        "alternate_id": null,
        "alternate_name": null,
        "rating": null,
        "type_of_assessment": null,
        "last_assessment_date": null,
        "core_values_assessment_date": null,
        "core_values_assessment": null,
        "vision_synced": true
    },
    {
        "id": 342,
        "partner_type": "Government",
        "cso_type": null,
        "name": "SIMORGH FILM (SFACA)",
        "short_name": "",
        "description": "",
        "shared_partner": "No",
        "address": "TAWHID E HASHT JABREAL DISTRIC",
        "email": null,
        "phone_number": "799240824",
        "vendor_number": 2500220962,
        "alternate_id": null,
        "alternate_name": null,
        "rating": "High",
        "type_of_assessment": "High Risk Assumed",
        "last_assessment_date": "2016-01-08",
        "core_values_assessment_date": null,
        "core_values_assessment": null,
        "vision_synced": true
    },
    {
        "id": 37,
        "partner_type": "Civil Society Organization",
        "cso_type": "National",
        "name": "SOCIAL AND HUMANITARIAN ASSISTANCE ORGANIZATION",
        "short_name": "",
        "description": "",
        "shared_partner": "No",
        "address": "AUB BUILDING ZARGHONA MAIDAN S",
        "email": "DIRECTOR.SHAO@YAHOO.COM",
        "phone_number": "0093-703859724",
        "vendor_number": 2500234420,
        "alternate_id": null,
        "alternate_name": null,
        "rating": "High",
        "type_of_assessment": "High Risk Assumed",
        "last_assessment_date": "2016-03-20",
        "core_values_assessment_date": "2016-03-31",
        "core_values_assessment": null,
        "vision_synced": true
    },
    {
        "id": 20,
        "partner_type": "Civil Society Organization",
        "cso_type": "National",
        "name": "SOCIAL AND HUMANITARINA ASSISTANCE ORGANIZATION (SHAO)",
        "short_name": "",
        "description": "",
        "shared_partner": "No",
        "address": "KANDAHAR CITY",
        "email": null,
        "phone_number": "700490641",
        "vendor_number": 2300000365,
        "alternate_id": null,
        "alternate_name": null,
        "rating": "High",
        "type_of_assessment": "FINANCIAL MANAGEMENT CAPT",
        "last_assessment_date": "2013-03-01",
        "core_values_assessment_date": null,
        "core_values_assessment": null,
        "vision_synced": true
    },
    {
        "id": 94,
        "partner_type": "Civil Society Organization",
        "cso_type": "National",
        "name": "SOCIAL ASSOCIATION FOR DEVELOPMENT OF AFGHANISTAN",
        "short_name": "",
        "description": "",
        "shared_partner": "No",
        "address": "HOUSE 14 KLOLA POSHTA MARKET",
        "email": "SADAORG_AFG@YAHOO.CO.UK",
        "phone_number": "0093-700301456",
        "vendor_number": 2500235008,
        "alternate_id": null,
        "alternate_name": null,
        "rating": "High",
        "type_of_assessment": "High Risk Assumed",
        "last_assessment_date": "2016-03-22",
        "core_values_assessment_date": "2016-03-22",
        "core_values_assessment": null,
        "vision_synced": true
    },
    {
        "id": 44,
        "partner_type": "Civil Society Organization",
        "cso_type": "National",
        "name": "SOCIAL ASSOCIATION FOR DEVELOPMENT OF AFGHANISTAN",
        "short_name": "",
        "description": "",
        "shared_partner": "No",
        "address": "KABUL KABUL CITY",
        "email": null,
        "phone_number": null,
        "vendor_number": 2500001605,
        "alternate_id": null,
        "alternate_name": null,
        "rating": "High",
        "type_of_assessment": "High Risk Assumed",
        "last_assessment_date": "2016-01-20",
        "core_values_assessment_date": "2016-01-09",
        "core_values_assessment": null,
        "vision_synced": true
    },
    {
        "id": 78,
        "partner_type": "Civil Society Organization",
        "cso_type": "National",
        "name": "SOCIAL DEVELOPMENT AND LEGAL RIGHTS",
        "short_name": "",
        "description": "",
        "shared_partner": "No",
        "address": "555 STREET 2 KARTE PARWAN",
        "email": null,
        "phone_number": "700669026",
        "vendor_number": 2300039790,
        "alternate_id": null,
        "alternate_name": null,
        "rating": "High",
        "type_of_assessment": "FINANCIAL MANAGEMENT CAPT",
        "last_assessment_date": "2012-06-01",
        "core_values_assessment_date": null,
        "core_values_assessment": null,
        "vision_synced": true
    },
    {
        "id": 25,
        "partner_type": "Civil Society Organization",
        "cso_type": "National",
        "name": "SOCIAL DEVELOPMENT AND LEGAL RIGHTS",
        "short_name": "",
        "description": "",
        "shared_partner": "No",
        "address": "555 STREET 2, KARTI PARWAN",
        "email": null,
        "phone_number": "700669026",
        "vendor_number": 2500220702,
        "alternate_id": null,
        "alternate_name": null,
        "rating": "High",
        "type_of_assessment": "High Risk Assumed",
        "last_assessment_date": "2016-01-08",
        "core_values_assessment_date": "2016-01-08",
        "core_values_assessment": null,
        "vision_synced": true
    },
    {
        "id": 33,
        "partner_type": "Civil Society Organization",
        "cso_type": null,
        "name": "SOCIAL HUMANITARIN ASSISTANCE ORG",
        "short_name": "",
        "description": "",
        "shared_partner": "No",
        "address": "KANDAHAR PD 06 SHAHRI NAW DAND",
        "email": null,
        "phone_number": "0794552722",
        "vendor_number": 2500001480,
        "alternate_id": null,
        "alternate_name": null,
        "rating": "High",
        "type_of_assessment": null,
        "last_assessment_date": null,
        "core_values_assessment_date": null,
        "core_values_assessment": null,
        "vision_synced": true
    },
    {
        "id": 56,
        "partner_type": "Civil Society Organization",
        "cso_type": "National",
        "name": "SOCIETY FOR SUSTAINABLE DEVELOPMENT AFGHANISTAN",
        "short_name": "",
        "description": "",
        "shared_partner": "No",
        "address": "HOUSE NO.2,STREET 1",
        "email": "SSDAFGHANISTAN@GMAIL.COM",
        "phone_number": "788788717",
        "vendor_number": 2500200136,
        "alternate_id": null,
        "alternate_name": null,
        "rating": "High",
        "type_of_assessment": null,
        "last_assessment_date": "2012-01-01",
        "core_values_assessment_date": null,
        "core_values_assessment": null,
        "vision_synced": true
    },
    {
        "id": 29,
        "partner_type": "Civil Society Organization",
        "cso_type": null,
        "name": "SOCIETY FOR SUSTAINABLE DEVELOPMENT OF AFGHANISTAN",
        "short_name": "",
        "description": "",
        "shared_partner": "No",
        "address": "HOUSE  02,",
        "email": null,
        "phone_number": "0777004780/78...",
        "vendor_number": 2300001131,
        "alternate_id": null,
        "alternate_name": null,
        "rating": "High",
        "type_of_assessment": "FINANCIAL MANAGEMENT CAPT",
        "last_assessment_date": "2012-01-01",
        "core_values_assessment_date": null,
        "core_values_assessment": null,
        "vision_synced": true
    },
    {
        "id": 517,
        "partner_type": "Government",
        "cso_type": null,
        "name": "SOHAILA",
        "short_name": "",
        "description": "",
        "shared_partner": "No",
        "address": "KABUL KABUL CITY CENTER",
        "email": "DR.SOHAILA1@GMAIL.COM",
        "phone_number": "0775574712",
        "vendor_number": 2300049647,
        "alternate_id": null,
        "alternate_name": null,
        "rating": null,
        "type_of_assessment": "MICRO ASST.",
        "last_assessment_date": "2011-12-31",
        "core_values_assessment_date": null,
        "core_values_assessment": null,
        "vision_synced": true
    },
    {
        "id": 58,
        "partner_type": "Civil Society Organization",
        "cso_type": "National",
        "name": "SOLIDARITY FOR AFGHAN FAMILIES",
        "short_name": "",
        "description": "",
        "shared_partner": "No",
        "address": null,
        "email": null,
        "phone_number": null,
        "vendor_number": 2500217364,
        "alternate_id": null,
        "alternate_name": null,
        "rating": null,
        "type_of_assessment": null,
        "last_assessment_date": null,
        "core_values_assessment_date": null,
        "core_values_assessment": null,
        "vision_synced": true
    },
    {
        "id": 765,
        "partner_type": "Government",
        "cso_type": null,
        "name": "SORAI TEGA CDC",
        "short_name": "",
        "description": "",
        "shared_partner": "No",
        "address": "SURKHROAD DISTRICT",
        "email": null,
        "phone_number": "0777590538",
        "vendor_number": 2500229108,
        "alternate_id": null,
        "alternate_name": null,
        "rating": "High",
        "type_of_assessment": "High Risk Assumed",
        "last_assessment_date": "2016-01-04",
        "core_values_assessment_date": null,
        "core_values_assessment": null,
        "vision_synced": true
    },
    {
        "id": 353,
        "partner_type": "Government",
        "cso_type": null,
        "name": "SPEEKKAI CDC",
        "short_name": "",
        "description": "",
        "shared_partner": "No",
        "address": "KUNAR ASMAR DISTRICT",
        "email": null,
        "phone_number": null,
        "vendor_number": 2500230404,
        "alternate_id": null,
        "alternate_name": null,
        "rating": "High",
        "type_of_assessment": "High Risk Assumed",
        "last_assessment_date": "2016-01-04",
        "core_values_assessment_date": null,
        "core_values_assessment": null,
        "vision_synced": true
    },
    {
        "id": 352,
        "partner_type": "Government",
        "cso_type": null,
        "name": "SRA MIRAN CDC",
        "short_name": "",
        "description": "",
        "shared_partner": "No",
        "address": "NANGARHAR HASKA MINA DISTRICT",
        "email": null,
        "phone_number": null,
        "vendor_number": 2500230430,
        "alternate_id": null,
        "alternate_name": null,
        "rating": "High",
        "type_of_assessment": "High Risk Assumed",
        "last_assessment_date": "2016-01-04",
        "core_values_assessment_date": null,
        "core_values_assessment": null,
        "vision_synced": true
    },
    {
        "id": 910,
        "partner_type": "Government",
        "cso_type": null,
        "name": "STATISTICS AFFAIRS DEPARTMENT (MOI)",
        "short_name": "",
        "description": "",
        "shared_partner": "No",
        "address": "KABUL",
        "email": "ASADNIAZY@YAHOO.COM",
        "phone_number": "0799325341",
        "vendor_number": 2500224357,
        "alternate_id": null,
        "alternate_name": null,
        "rating": "High",
        "type_of_assessment": "High Risk Assumed",
        "last_assessment_date": "2016-01-04",
        "core_values_assessment_date": null,
        "core_values_assessment": null,
        "vision_synced": true
    },
    {
        "id": 81,
        "partner_type": "Civil Society Organization",
        "cso_type": "International",
        "name": "SWEDISH COMMITTEE FOR AFGHANISTAN (",
        "short_name": "",
        "description": "",
        "shared_partner": "No",
        "address": "JALALABAD ROAD PAKTIA KOT",
        "email": "NABI.DEHZAD@SCA.ORG.AF",
        "phone_number": "799175853",
        "vendor_number": 2500200042,
        "alternate_id": null,
        "alternate_name": null,
        "rating": "High",
        "type_of_assessment": "High Risk Assumed",
        "last_assessment_date": "2016-01-20",
        "core_values_assessment_date": "2013-07-25",
        "core_values_assessment": null,
        "vision_synced": true
    },
    {
        "id": 16,
        "partner_type": "Civil Society Organization",
        "cso_type": "National",
        "name": "TABISH SOCIAL HEALTH EDUCATION ORG",
        "short_name": "",
        "description": "",
        "shared_partner": "No",
        "address": "KABUL KHUSHAL KHAN MINA",
        "email": "ARIA_POPAL@HOTMAIL.COM",
        "phone_number": "0700257340",
        "vendor_number": 2500222286,
        "alternate_id": null,
        "alternate_name": null,
        "rating": "High",
        "type_of_assessment": "High Risk Assumed",
        "last_assessment_date": "2012-06-01",
        "core_values_assessment_date": "2016-01-07",
        "core_values_assessment": null,
        "vision_synced": true
    },
    {
        "id": 347,
        "partner_type": "Government",
        "cso_type": null,
        "name": "TAIMOOR SHAH ESHQZAI",
        "short_name": "",
        "description": "",
        "shared_partner": "No",
        "address": "KABUL CITY CENTER",
        "email": "TAIMOOR_SVF@YAHOO.COM",
        "phone_number": "0796060924",
        "vendor_number": 2300066039,
        "alternate_id": null,
        "alternate_name": null,
        "rating": null,
        "type_of_assessment": null,
        "last_assessment_date": null,
        "core_values_assessment_date": null,
        "core_values_assessment": null,
        "vision_synced": true
    },
    {
        "id": 377,
        "partner_type": "Government",
        "cso_type": null,
        "name": "TAKHTA PUL H.ZAHIR VILLAGE CDC",
        "short_name": "",
        "description": "",
        "shared_partner": "No",
        "address": "KANDAHAR CITY",
        "email": null,
        "phone_number": null,
        "vendor_number": 2500227311,
        "alternate_id": null,
        "alternate_name": null,
        "rating": "High",
        "type_of_assessment": "High Risk Assumed",
        "last_assessment_date": "2016-01-04",
        "core_values_assessment_date": null,
        "core_values_assessment": null,
        "vision_synced": true
    },
    {
        "id": 69,
        "partner_type": "Civil Society Organization",
        "cso_type": "International",
        "name": "TEARFUND",
        "short_name": "",
        "description": "",
        "shared_partner": "No",
        "address": "ZAMBAQ SQUARE KABUL AFGHANISTA",
        "email": null,
        "phone_number": null,
        "vendor_number": 2500001246,
        "alternate_id": null,
        "alternate_name": null,
        "rating": "High",
        "type_of_assessment": "High Risk Assumed",
        "last_assessment_date": "2016-01-02",
        "core_values_assessment_date": null,
        "core_values_assessment": null,
        "vision_synced": true
    },
    {
        "id": 62,
        "partner_type": "Civil Society Organization",
        "cso_type": "International",
        "name": "TEAR FUND",
        "short_name": "",
        "description": "",
        "shared_partner": "No",
        "address": "HOUSE NO. 518 STREET 9",
        "email": null,
        "phone_number": "797745560",
        "vendor_number": 2500200130,
        "alternate_id": null,
        "alternate_name": null,
        "rating": "High",
        "type_of_assessment": "High Risk Assumed",
        "last_assessment_date": "2016-01-20",
        "core_values_assessment_date": "2013-07-25",
        "core_values_assessment": null,
        "vision_synced": true
    },
    {
        "id": 22,
        "partner_type": "Civil Society Organization",
        "cso_type": "National",
        "name": "THE AGA KHAN UNIVERSITY",
        "short_name": "",
        "description": "",
        "shared_partner": "No",
        "address": "STADIUM ROAD, P.O. BOX 3500",
        "email": null,
        "phone_number": null,
        "vendor_number": 2300017868,
        "alternate_id": null,
        "alternate_name": null,
        "rating": null,
        "type_of_assessment": null,
        "last_assessment_date": null,
        "core_values_assessment_date": null,
        "core_values_assessment": null,
        "vision_synced": true
    },
    {
        "id": 31,
        "partner_type": "Civil Society Organization",
        "cso_type": "International",
        "name": "THE AGA KHAN UNIVERSITY",
        "short_name": "",
        "description": "",
        "shared_partner": "No",
        "address": "STADIUM ROAD, KARCHI, 74800, P",
        "email": null,
        "phone_number": null,
        "vendor_number": 2500001535,
        "alternate_id": null,
        "alternate_name": null,
        "rating": "High",
        "type_of_assessment": null,
        "last_assessment_date": null,
        "core_values_assessment_date": null,
        "core_values_assessment": null,
        "vision_synced": true
    },
    {
        "id": 65,
        "partner_type": "Civil Society Organization",
        "cso_type": "National",
        "name": "THE WOMANITY FOUNDATION",
        "short_name": "",
        "description": "",
        "shared_partner": "No",
        "address": "DISTRICT 10 SHARE NAW BURJ-E-",
        "email": "INFO@WOMANITY.ORG",
        "phone_number": "0797595992",
        "vendor_number": 2300061728,
        "alternate_id": null,
        "alternate_name": null,
        "rating": null,
        "type_of_assessment": null,
        "last_assessment_date": null,
        "core_values_assessment_date": null,
        "core_values_assessment": null,
        "vision_synced": true
    },
    {
        "id": 950,
        "partner_type": "Government",
        "cso_type": null,
        "name": "TISHA SIRI CDC",
        "short_name": "",
        "description": "",
        "shared_partner": "No",
        "address": "KUNAR ASSADABAD DISTRICT",
        "email": null,
        "phone_number": null,
        "vendor_number": 2500230256,
        "alternate_id": null,
        "alternate_name": null,
        "rating": "High",
        "type_of_assessment": "High Risk Assumed",
        "last_assessment_date": "2016-01-04",
        "core_values_assessment_date": null,
        "core_values_assessment": null,
        "vision_synced": true
    },
    {
        "id": 762,
        "partner_type": "UN Agency",
        "cso_type": null,
        "name": "UN-HABITAT",
        "short_name": "",
        "description": "",
        "shared_partner": "No",
        "address": "TAIMANI MAIN STREET",
        "email": null,
        "phone_number": null,
        "vendor_number": 2500200007,
        "alternate_id": null,
        "alternate_name": null,
        "rating": null,
        "type_of_assessment": null,
        "last_assessment_date": null,
        "core_values_assessment_date": null,
        "core_values_assessment": null,
        "vision_synced": true
    },
    {
        "id": 853,
        "partner_type": "UN Agency",
        "cso_type": null,
        "name": "UNITED NATIONS ASSISTANCE MISSION IN AFGHANISTAN",
        "short_name": "",
        "description": "",
        "shared_partner": "No",
        "address": "UNOCA COMPOUND JALALABAD ROAD",
        "email": null,
        "phone_number": null,
        "vendor_number": 2500200200,
        "alternate_id": null,
        "alternate_name": null,
        "rating": null,
        "type_of_assessment": null,
        "last_assessment_date": null,
        "core_values_assessment_date": null,
        "core_values_assessment": null,
        "vision_synced": true
    },
    {
        "id": 79,
        "partner_type": "Civil Society Organization",
        "cso_type": "International",
        "name": "VALID INTERNATIONAL LTD",
        "short_name": "",
        "description": "",
        "shared_partner": "No",
        "address": "35 LEOPOLD STREET, OXFORD, OX4",
        "email": "OFFICE@VALIDINTERNATIONAL.ORG",
        "phone_number": "44-186-5722-180",
        "vendor_number": 2500000771,
        "alternate_id": null,
        "alternate_name": null,
        "rating": null,
        "type_of_assessment": null,
        "last_assessment_date": null,
        "core_values_assessment_date": null,
        "core_values_assessment": null,
        "vision_synced": true
    },
    {
        "id": 855,
        "partner_type": "Government",
        "cso_type": null,
        "name": "VITAL STATISTIC DEPARTMENT HELMAND",
        "short_name": "",
        "description": "",
        "shared_partner": "No",
        "address": "CITY CENTER HELMAND",
        "email": null,
        "phone_number": null,
        "vendor_number": 2500226574,
        "alternate_id": null,
        "alternate_name": null,
        "rating": "High",
        "type_of_assessment": "High Risk Assumed",
        "last_assessment_date": "2016-01-04",
        "core_values_assessment_date": null,
        "core_values_assessment": null,
        "vision_synced": true
    },
    {
        "id": 838,
        "partner_type": "Government",
        "cso_type": null,
        "name": "VITAL STATISTIC OFFICE KANDAHAR",
        "short_name": "",
        "description": "",
        "shared_partner": "No",
        "address": "KANDAHAR",
        "email": null,
        "phone_number": null,
        "vendor_number": 2500224368,
        "alternate_id": null,
        "alternate_name": null,
        "rating": "High",
        "type_of_assessment": "High Risk Assumed",
        "last_assessment_date": "2016-01-04",
        "core_values_assessment_date": null,
        "core_values_assessment": null,
        "vision_synced": true
    },
    {
        "id": 163,
        "partner_type": "Government",
        "cso_type": null,
        "name": "VSD BAMYAN",
        "short_name": "",
        "description": "",
        "shared_partner": "No",
        "address": "BAMYAN CITY",
        "email": null,
        "phone_number": "0777574333",
        "vendor_number": 2500224377,
        "alternate_id": null,
        "alternate_name": null,
        "rating": "High",
        "type_of_assessment": "High Risk Assumed",
        "last_assessment_date": "2016-01-04",
        "core_values_assessment_date": null,
        "core_values_assessment": null,
        "vision_synced": true
    },
    {
        "id": 617,
        "partner_type": "Government",
        "cso_type": null,
        "name": "VSD PANJSHIR VITAL STATISTICS DEPARTMENT",
        "short_name": "",
        "description": "",
        "shared_partner": "No",
        "address": "PANJSHIR BAZARAK PANJSHIR",
        "email": null,
        "phone_number": "0777882797",
        "vendor_number": 2500233283,
        "alternate_id": null,
        "alternate_name": null,
        "rating": "High",
        "type_of_assessment": "High Risk Assumed",
        "last_assessment_date": "2016-01-02",
        "core_values_assessment_date": null,
        "core_values_assessment": null,
        "vision_synced": true
    },
    {
        "id": 943,
        "partner_type": "Civil Society Organization",
        "cso_type": "National",
        "name": "V.W.O",
        "short_name": "",
        "description": "",
        "shared_partner": "No",
        "address": "BAADMORGHAN",
        "email": "PCOORDVWO@YAHOO.COM",
        "phone_number": "93789706200",
        "vendor_number": 2500200008,
        "alternate_id": null,
        "alternate_name": null,
        "rating": "High",
        "type_of_assessment": "High Risk Assumed",
        "last_assessment_date": "2016-01-20",
        "core_values_assessment_date": "2016-01-20",
        "core_values_assessment": null,
        "vision_synced": true
    },
    {
        "id": 301,
        "partner_type": "Government",
        "cso_type": null,
        "name": "WAHABULLAH KHALILI",
        "short_name": "",
        "description": "",
        "shared_partner": "No",
        "address": "DISTRICT8, KART-E- NAW KABUL",
        "email": "WAHAB_KHALILI@HOTMAIL.COM",
        "phone_number": "0700983874",
        "vendor_number": 2300063895,
        "alternate_id": null,
        "alternate_name": null,
        "rating": null,
        "type_of_assessment": null,
        "last_assessment_date": null,
        "core_values_assessment_date": null,
        "core_values_assessment": null,
        "vision_synced": true
    },
    {
        "id": 768,
        "partner_type": "Government",
        "cso_type": null,
        "name": "WAHID YAR CONSTRUCTION CO",
        "short_name": "",
        "description": "",
        "shared_partner": "No",
        "address": "BAGHLAN",
        "email": null,
        "phone_number": null,
        "vendor_number": 2500224344,
        "alternate_id": null,
        "alternate_name": null,
        "rating": "High",
        "type_of_assessment": null,
        "last_assessment_date": null,
        "core_values_assessment_date": null,
        "core_values_assessment": null,
        "vision_synced": true
    },
    {
        "id": 854,
        "partner_type": "Government",
        "cso_type": null,
        "name": "WAIS",
        "short_name": "",
        "description": "",
        "shared_partner": "No",
        "address": "KANDAHAR AFGHANISTAN",
        "email": null,
        "phone_number": null,
        "vendor_number": 2300042653,
        "alternate_id": null,
        "alternate_name": null,
        "rating": "Low",
        "type_of_assessment": "PRE ASSTMNT",
        "last_assessment_date": "2012-01-01",
        "core_values_assessment_date": null,
        "core_values_assessment": null,
        "vision_synced": true
    },
    {
        "id": 826,
        "partner_type": "Government",
        "cso_type": null,
        "name": "WAKIL AHMAD BAREKZAI",
        "short_name": "",
        "description": "",
        "shared_partner": "No",
        "address": "MARKET MAKRORAIAN KOHNA, MOLSA",
        "email": null,
        "phone_number": "0798918662",
        "vendor_number": 2300037983,
        "alternate_id": null,
        "alternate_name": null,
        "rating": "Significant",
        "type_of_assessment": "MICRO ASSESSMENT",
        "last_assessment_date": "2011-11-20",
        "core_values_assessment_date": null,
        "core_values_assessment": null,
        "vision_synced": true
    },
    {
        "id": 30,
        "partner_type": "Civil Society Organization",
        "cso_type": "International",
        "name": "WAR CHILD CANADA",
        "short_name": "",
        "description": "",
        "shared_partner": "No",
        "address": "KABUL CITY CENTER",
        "email": "LISAP@WARCHILD.CA",
        "phone_number": null,
        "vendor_number": 2500001240,
        "alternate_id": null,
        "alternate_name": null,
        "rating": "High",
        "type_of_assessment": "High Risk Assumed",
        "last_assessment_date": "2016-01-20",
        "core_values_assessment_date": null,
        "core_values_assessment": null,
        "vision_synced": true
    },
    {
        "id": 11,
        "partner_type": "Civil Society Organization",
        "cso_type": "International",
        "name": "WAR CHILD UK",
        "short_name": "",
        "description": "",
        "shared_partner": "No",
        "address": "HERAT CITY",
        "email": null,
        "phone_number": null,
        "vendor_number": 2500200009,
        "alternate_id": null,
        "alternate_name": null,
        "rating": "High",
        "type_of_assessment": "High Risk Assumed",
        "last_assessment_date": "2016-01-20",
        "core_values_assessment_date": "2013-07-26",
        "core_values_assessment": null,
        "vision_synced": true
    },
    {
        "id": 68,
        "partner_type": "Civil Society Organization",
        "cso_type": null,
        "name": "WAR CHILD (UK)",
        "short_name": "",
        "description": "",
        "shared_partner": "No",
        "address": "JADE MAHTAB, NAZAR QALA NOWI S",
        "email": null,
        "phone_number": "795663615",
        "vendor_number": 2500220961,
        "alternate_id": null,
        "alternate_name": null,
        "rating": null,
        "type_of_assessment": null,
        "last_assessment_date": null,
        "core_values_assessment_date": null,
        "core_values_assessment": null,
        "vision_synced": true
    },
    {
        "id": 71,
        "partner_type": "Civil Society Organization",
        "cso_type": "National",
        "name": "W.O.D.O",
        "short_name": "",
        "description": "",
        "shared_partner": "No",
        "address": "BAMYAN ZARGARAN BAMYAN PROVINC",
        "email": "WODO2011AF@UNICEF.ORG",
        "phone_number": "0797340438",
        "vendor_number": 2300049404,
        "alternate_id": null,
        "alternate_name": null,
        "rating": "High",
        "type_of_assessment": null,
        "last_assessment_date": null,
        "core_values_assessment_date": null,
        "core_values_assessment": null,
        "vision_synced": true
    },
    {
        "id": 720,
        "partner_type": "Government",
        "cso_type": null,
        "name": "YAKA TOOT SHAMAL",
        "short_name": "",
        "description": "",
        "shared_partner": "No",
        "address": "HERAT",
        "email": null,
        "phone_number": null,
        "vendor_number": 2500224279,
        "alternate_id": null,
        "alternate_name": null,
        "rating": "High",
        "type_of_assessment": "High Risk Assumed",
        "last_assessment_date": "2016-01-04",
        "core_values_assessment_date": null,
        "core_values_assessment": null,
        "vision_synced": true
    },
    {
        "id": 274,
        "partner_type": "Government",
        "cso_type": null,
        "name": "YICC-DEPARTMENT OF CULTURE AND YOUTH, NANGARHAR",
        "short_name": "",
        "description": "",
        "shared_partner": "No",
        "address": "NANGARHAR PROVINCE",
        "email": null,
        "phone_number": null,
        "vendor_number": 2500200011,
        "alternate_id": null,
        "alternate_name": null,
        "rating": "High",
        "type_of_assessment": "High Risk Assumed",
        "last_assessment_date": "2016-01-20",
        "core_values_assessment_date": null,
        "core_values_assessment": null,
        "vision_synced": true
    },
    {
        "id": 529,
        "partner_type": "Government",
        "cso_type": null,
        "name": "YICC HELMAND CENTRE-HELMAND",
        "short_name": "",
        "description": "",
        "shared_partner": "No",
        "address": null,
        "email": null,
        "phone_number": "703052325",
        "vendor_number": 2500200321,
        "alternate_id": null,
        "alternate_name": null,
        "rating": "High",
        "type_of_assessment": "High Risk Assumed",
        "last_assessment_date": "2016-01-20",
        "core_values_assessment_date": null,
        "core_values_assessment": null,
        "vision_synced": true
    },
    {
        "id": 239,
        "partner_type": "Government",
        "cso_type": null,
        "name": "YICC-KABUL",
        "short_name": "",
        "description": "",
        "shared_partner": "No",
        "address": "KABUL KABUL CITY",
        "email": null,
        "phone_number": "0799116914",
        "vendor_number": 2500221853,
        "alternate_id": null,
        "alternate_name": null,
        "rating": "High",
        "type_of_assessment": "High Risk Assumed",
        "last_assessment_date": "2016-01-08",
        "core_values_assessment_date": null,
        "core_values_assessment": null,
        "vision_synced": true
    },
    {
        "id": 810,
        "partner_type": "Government",
        "cso_type": null,
        "name": "YICC NIMROZ",
        "short_name": "",
        "description": "",
        "shared_partner": "No",
        "address": "NIMROZ NIMROZ",
        "email": null,
        "phone_number": null,
        "vendor_number": 2500215285,
        "alternate_id": null,
        "alternate_name": null,
        "rating": "High",
        "type_of_assessment": "High Risk Assumed",
        "last_assessment_date": "2016-01-20",
        "core_values_assessment_date": null,
        "core_values_assessment": null,
        "vision_synced": true
    },
    {
        "id": 524,
        "partner_type": "Government",
        "cso_type": null,
        "name": "ZABUL DIRECTORATE OF LABOR AND SOCAIL AFFIARS",
        "short_name": "",
        "description": "",
        "shared_partner": "No",
        "address": "LIWA STREET QALAT",
        "email": null,
        "phone_number": "93790001559",
        "vendor_number": 2500233992,
        "alternate_id": null,
        "alternate_name": null,
        "rating": "High",
        "type_of_assessment": "High Risk Assumed",
        "last_assessment_date": "2016-01-20",
        "core_values_assessment_date": null,
        "core_values_assessment": null,
        "vision_synced": true
    },
    {
        "id": 61,
        "partner_type": "Civil Society Organization",
        "cso_type": "International",
        "name": "ZOA REFUGEE CORE NORTH",
        "short_name": "",
        "description": "",
        "shared_partner": "No",
        "address": "JAWZJAN BANDAR ANDKHOY SHEBERG",
        "email": null,
        "phone_number": "0798996237",
        "vendor_number": 2500001524,
        "alternate_id": null,
        "alternate_name": null,
        "rating": null,
        "type_of_assessment": null,
        "last_assessment_date": null,
        "core_values_assessment_date": null,
        "core_values_assessment": null,
        "vision_synced": true
    },
    {
        "id": 546,
        "partner_type": "Government",
        "cso_type": null,
        "name": "ZULMAI",
        "short_name": "",
        "description": "",
        "shared_partner": "No",
        "address": "BAMYAN CENTRAL REGION",
        "email": null,
        "phone_number": "0798507278",
        "vendor_number": 2300043367,
        "alternate_id": null,
        "alternate_name": null,
        "rating": null,
        "type_of_assessment": null,
        "last_assessment_date": null,
        "core_values_assessment_date": null,
        "core_values_assessment": null,
        "vision_synced": true
    }
]
